memcache.py
python_memcached-1.61.dist-info/METADATA
python_memcached-1.61.dist-info/WHEEL
python_memcached-1.61.dist-info/top_level.txt
python_memcached-1.61.dist-info/RECORD
