Metadata-Version: 2.1
Name: python-memcached
Version: 1.61
Summary: Pure python memcached client
Home-page: https://github.com/linsomniac/python-memcached
Download-URL: https://github.com/linsomniac/python-memcached/releases/download/1.61/python-memcached-1.61.tar.gz
Author: Evan Martin
Author-email: martine@danga.com
Maintainer: Sean Reifschneider
Maintainer-email: jafo00@gmail.com
Classifier: Development Status :: 5 - Production/Stable
Classifier: Intended Audience :: Developers
Classifier: License :: OSI Approved :: Python Software Foundation License
Classifier: Operating System :: OS Independent
Classifier: Programming Language :: Python
Classifier: Topic :: Internet
Classifier: Topic :: Software Development :: Libraries :: Python Modules
Classifier: Programming Language :: Python
Classifier: Programming Language :: Python :: 3
Classifier: Programming Language :: Python :: 3.6
Classifier: Programming Language :: Python :: 3.7
Classifier: Programming Language :: Python :: 3.8
Classifier: Programming Language :: Python :: 3.9
Classifier: Programming Language :: Python :: 3.10
Classifier: Programming Language :: Python :: 3.11
Classifier: Programming Language :: Python :: 3.12
